mastercardmastercom/__init__.py
mastercardmastercom/casefiling.py
mastercardmastercom/chargebacks.py
mastercardmastercom/chargebacksdebitmastercardandeuropedualacquirer.py
mastercardmastercom/claims.py
mastercardmastercom/fees.py
mastercardmastercom/feesdebitmastercardandeuropedualacquirer.py
mastercardmastercom/fraud.py
mastercardmastercom/healthcheck.py
mastercardmastercom/migrateddisputes.py
mastercardmastercom/queues.py
mastercardmastercom/reconciliation.py
mastercardmastercom/resourceconfig.py
mastercardmastercom/retrievals.py
mastercardmastercom/retrievalsdebitmastercardandeuropedualacquirer.py
mastercardmastercom/transactions.py
mastercardmastercom/transactionsdebitmastercardandeuropedualacquirer.py
mastercard_mastercom-6.0.0.dist-info/LICENSE
mastercard_mastercom-6.0.0.dist-info/METADATA
mastercard_mastercom-6.0.0.dist-info/WHEEL
mastercard_mastercom-6.0.0.dist-info/top_level.txt
mastercard_mastercom-6.0.0.dist-info/RECORD
